setuptools_dso/__init__.py
setuptools_dso/compiler.py
setuptools_dso/dsocmd.py
setuptools_dso/probe.py
setuptools_dso/runtime.py
setuptools_dso/test/__init__.py
setuptools_dso/test/test_parallel.py
setuptools_dso/test/test_probe.py
setuptools_dso-2.12.2.dist-info/licenses/LICENSE
setuptools_dso-2.12.2.dist-info/METADATA
setuptools_dso-2.12.2.dist-info/WHEEL
setuptools_dso-2.12.2.dist-info/top_level.txt
setuptools_dso-2.12.2.dist-info/RECORD
