Metadata-Version: 2.1
Name: setuptools_dso
Version: 2.12.2
Summary: setuptools extension to build non-python shared libraries
Home-page: https://github.com/mdavidsaver/setuptools_dso
Author: Michael Davidsaver
Author-email: mdavidsaver@gmail.com
License: BSD
Project-URL: Documentation, https://mdavidsaver.github.io/setuptools_dso
Project-URL: Release Notes, https://mdavidsaver.github.io/setuptools_dso/releasenotes.html
Classifier: Development Status :: 5 - Production/Stable
Classifier: Programming Language :: Python :: 2.7
Classifier: Programming Language :: Python :: 3
Classifier: Intended Audience :: Developers
Classifier: Topic :: Software Development :: Libraries :: Python Modules
Classifier: Topic :: System :: Archiving :: Packaging
Classifier: Framework :: Setuptools Plugin
Classifier: License :: OSI Approved :: BSD License
Requires-Python: >=2.7
License-File: LICENSE
